cobra_color/__init__.py
cobra_color/format.py
cobra_color/output.py
cobra_color/types.py
cobra_color/render/__init__.py
cobra_color/render/_ansi_art.py
cobra_color/render/_utils.py
cobra_color/render/fonts/__init__.py
cobra_color/render/fonts/_font_map.py
cobra_color/string/__init__.py
cobra_color/string/_color.py
cobra_color/string/_extension.py
cobra_color/string/_segment.py
cobra_color/string/_utils.py
cobra_color-1.2.0.dist-info/licenses/LICENSE
cobra_color-1.2.0.dist-info/METADATA
cobra_color-1.2.0.dist-info/WHEEL
cobra_color-1.2.0.dist-info/top_level.txt
cobra_color-1.2.0.dist-info/RECORD
