Metadata-Version: 2.4
Name: cobra-color
Version: 1.2.0
Summary: A Python library for enhanced terminal display.
Author-email: Zhen Tian <zhen.tian.cs@gmail.com>
Project-URL: Homepage, https://github.com/tinchen777/cobra-color.git
Project-URL: Repository, https://github.com/tinchen777/cobra-color.git
Project-URL: Issues, https://github.com/tinchen777/cobra-color.git/issues
Classifier: Programming Language :: Python :: 3
Classifier: Programming Language :: Python :: 3.9
Classifier: Programming Language :: Python :: 3.10
Classifier: Programming Language :: Python :: 3.11
Classifier: Programming Language :: Python :: 3.12
Classifier: Programming Language :: Python :: 3.13
Classifier: Programming Language :: Python :: 3.14
Requires-Python: >=3.9
License-File: LICENSE
Requires-Dist: Pillow<11,>=9.0
Requires-Dist: numpy<2.0,>=1.21
Dynamic: license-file
